{
  "id": "178ee743-b1dc-47aa-8424-a1b49ddd2270",
  "prevId": "b2f1a6bf-ceb5-4133-b588-1a24ea83cd50",
  "version": "7",
  "dialect": "postgresql",
  "tables": {
    "public.organizations": {
      "name": "organizations",
      "schema": "",
      "columns": {
        "id": {
          "name": "id",
          "type": "serial",
          "primaryKey": true,
          "notNull": true
        },
        "name": {
          "name": "name",
          "type": "text",
          "primaryKey": false,
          "notNull": true
        },
        "description": {
          "name": "description",
          "type": "text",
          "primaryKey": false,
          "notNull": false
        },
        "created_at": {
          "name": "created_at",
          "type": "timestamp",
          "primaryKey": false,
          "notNull": true,
          "default": "now()"
        }
      },
      "indexes": {},
      "foreignKeys": {},
      "compositePrimaryKeys": {},
      "uniqueConstraints": {},
      "policies": {},
      "checkConstraints": {},
      "isRLSEnabled": false
    },
    "public.profiles": {
      "name": "profiles",
      "schema": "",
      "columns": {
        "id": {
          "name": "id",
          "type": "uuid",
          "primaryKey": true,
          "notNull": true
        },
        "email": {
          "name": "email",
          "type": "text",
          "primaryKey": false,
          "notNull": true
        },
        "display_name": {
          "name": "display_name",
          "type": "text",
          "primaryKey": false,
          "notNull": false
        },
        "phone": {
          "name": "phone",
          "type": "text",
          "primaryKey": false,
          "notNull": false
        },
        "created_at": {
          "name": "created_at",
          "type": "timestamp",
          "primaryKey": false,
          "notNull": true,
          "default": "now()"
        }
      },
      "indexes": {},
      "foreignKeys": {},
      "compositePrimaryKeys": {},
      "uniqueConstraints": {},
      "policies": {},
      "checkConstraints": {},
      "isRLSEnabled": false
    },
    "public.todo_media": {
      "name": "todo_media",
      "schema": "",
      "columns": {
        "id": {
          "name": "id",
          "type": "serial",
          "primaryKey": true,
          "notNull": true
        },
        "todo_id": {
          "name": "todo_id",
          "type": "integer",
          "primaryKey": false,
          "notNull": true
        },
        "media_type": {
          "name": "media_type",
          "type": "text",
          "primaryKey": false,
          "notNull": true
        },
        "url": {
          "name": "url",
          "type": "text",
          "primaryKey": false,
          "notNull": true
        },
        "path": {
          "name": "path",
          "type": "text",
          "primaryKey": false,
          "notNull": true
        },
        "created_at": {
          "name": "created_at",
          "type": "timestamp",
          "primaryKey": false,
          "notNull": true,
          "default": "now()"
        }
      },
      "indexes": {},
      "foreignKeys": {
        "todo_media_todo_id_todos_id_fk": {
          "name": "todo_media_todo_id_todos_id_fk",
          "tableFrom": "todo_media",
          "tableTo": "todos",
          "columnsFrom": [
            "todo_id"
          ],
          "columnsTo": [
            "id"
          ],
          "onDelete": "cascade",
          "onUpdate": "no action"
        }
      },
      "compositePrimaryKeys": {},
      "uniqueConstraints": {},
      "policies": {},
      "checkConstraints": {},
      "isRLSEnabled": false
    },
    "public.todo_organizations": {
      "name": "todo_organizations",
      "schema": "",
      "columns": {
        "todo_id": {
          "name": "todo_id",
          "type": "integer",
          "primaryKey": false,
          "notNull": true
        },
        "organization_id": {
          "name": "organization_id",
          "type": "integer",
          "primaryKey": false,
          "notNull": true
        }
      },
      "indexes": {},
      "foreignKeys": {
        "todo_organizations_todo_id_todos_id_fk": {
          "name": "todo_organizations_todo_id_todos_id_fk",
          "tableFrom": "todo_organizations",
          "tableTo": "todos",
          "columnsFrom": [
            "todo_id"
          ],
          "columnsTo": [
            "id"
          ],
          "onDelete": "cascade",
          "onUpdate": "no action"
        },
        "todo_organizations_organization_id_organizations_id_fk": {
          "name": "todo_organizations_organization_id_organizations_id_fk",
          "tableFrom": "todo_organizations",
          "tableTo": "organizations",
          "columnsFrom": [
            "organization_id"
          ],
          "columnsTo": [
            "id"
          ],
          "onDelete": "cascade",
          "onUpdate": "no action"
        }
      },
      "compositePrimaryKeys": {
        "todo_organizations_todo_id_organization_id_pk": {
          "name": "todo_organizations_todo_id_organization_id_pk",
          "columns": [
            "todo_id",
            "organization_id"
          ]
        }
      },
      "uniqueConstraints": {},
      "policies": {},
      "checkConstraints": {},
      "isRLSEnabled": false
    },
    "public.todo_relationships": {
      "name": "todo_relationships",
      "schema": "",
      "columns": {
        "parent_id": {
          "name": "parent_id",
          "type": "integer",
          "primaryKey": false,
          "notNull": true
        },
        "child_id": {
          "name": "child_id",
          "type": "integer",
          "primaryKey": false,
          "notNull": true
        }
      },
      "indexes": {},
      "foreignKeys": {
        "todo_relationships_parent_id_todos_id_fk": {
          "name": "todo_relationships_parent_id_todos_id_fk",
          "tableFrom": "todo_relationships",
          "tableTo": "todos",
          "columnsFrom": [
            "parent_id"
          ],
          "columnsTo": [
            "id"
          ],
          "onDelete": "cascade",
          "onUpdate": "no action"
        },
        "todo_relationships_child_id_todos_id_fk": {
          "name": "todo_relationships_child_id_todos_id_fk",
          "tableFrom": "todo_relationships",
          "tableTo": "todos",
          "columnsFrom": [
            "child_id"
          ],
          "columnsTo": [
            "id"
          ],
          "onDelete": "cascade",
          "onUpdate": "no action"
        }
      },
      "compositePrimaryKeys": {
        "todo_relationships_parent_id_child_id_pk": {
          "name": "todo_relationships_parent_id_child_id_pk",
          "columns": [
            "parent_id",
            "child_id"
          ]
        }
      },
      "uniqueConstraints": {},
      "policies": {},
      "checkConstraints": {},
      "isRLSEnabled": false
    },
    "public.todos": {
      "name": "todos",
      "schema": "",
      "columns": {
        "id": {
          "name": "id",
          "type": "serial",
          "primaryKey": true,
          "notNull": true
        },
        "text": {
          "name": "text",
          "type": "text",
          "primaryKey": false,
          "notNull": true
        },
        "description": {
          "name": "description",
          "type": "text",
          "primaryKey": false,
          "notNull": false
        },
        "done": {
          "name": "done",
          "type": "boolean",
          "primaryKey": false,
          "notNull": true,
          "default": false
        },
        "is_pinned": {
          "name": "is_pinned",
          "type": "boolean",
          "primaryKey": false,
          "notNull": true,
          "default": false
        },
        "user_id": {
          "name": "user_id",
          "type": "uuid",
          "primaryKey": false,
          "notNull": true
        },
        "sequence": {
          "name": "sequence",
          "type": "integer",
          "primaryKey": false,
          "notNull": true,
          "default": 0
        },
        "created_at": {
          "name": "created_at",
          "type": "timestamp",
          "primaryKey": false,
          "notNull": true,
          "default": "now()"
        }
      },
      "indexes": {},
      "foreignKeys": {},
      "compositePrimaryKeys": {},
      "uniqueConstraints": {},
      "policies": {},
      "checkConstraints": {},
      "isRLSEnabled": false
    },
    "public.user_management_relationships": {
      "name": "user_management_relationships",
      "schema": "",
      "columns": {
        "manager_id": {
          "name": "manager_id",
          "type": "uuid",
          "primaryKey": false,
          "notNull": true
        },
        "managed_user_id": {
          "name": "managed_user_id",
          "type": "uuid",
          "primaryKey": false,
          "notNull": true
        }
      },
      "indexes": {},
      "foreignKeys": {
        "user_management_relationships_manager_id_profiles_id_fk": {
          "name": "user_management_relationships_manager_id_profiles_id_fk",
          "tableFrom": "user_management_relationships",
          "tableTo": "profiles",
          "columnsFrom": [
            "manager_id"
          ],
          "columnsTo": [
            "id"
          ],
          "onDelete": "cascade",
          "onUpdate": "no action"
        },
        "user_management_relationships_managed_user_id_profiles_id_fk": {
          "name": "user_management_relationships_managed_user_id_profiles_id_fk",
          "tableFrom": "user_management_relationships",
          "tableTo": "profiles",
          "columnsFrom": [
            "managed_user_id"
          ],
          "columnsTo": [
            "id"
          ],
          "onDelete": "cascade",
          "onUpdate": "no action"
        }
      },
      "compositePrimaryKeys": {
        "user_management_relationships_manager_id_managed_user_id_pk": {
          "name": "user_management_relationships_manager_id_managed_user_id_pk",
          "columns": [
            "manager_id",
            "managed_user_id"
          ]
        }
      },
      "uniqueConstraints": {},
      "policies": {},
      "checkConstraints": {},
      "isRLSEnabled": false
    },
    "public.user_organizations": {
      "name": "user_organizations",
      "schema": "",
      "columns": {
        "user_id": {
          "name": "user_id",
          "type": "uuid",
          "primaryKey": false,
          "notNull": true
        },
        "organization_id": {
          "name": "organization_id",
          "type": "integer",
          "primaryKey": false,
          "notNull": true
        }
      },
      "indexes": {},
      "foreignKeys": {
        "user_organizations_user_id_profiles_id_fk": {
          "name": "user_organizations_user_id_profiles_id_fk",
          "tableFrom": "user_organizations",
          "tableTo": "profiles",
          "columnsFrom": [
            "user_id"
          ],
          "columnsTo": [
            "id"
          ],
          "onDelete": "cascade",
          "onUpdate": "no action"
        },
        "user_organizations_organization_id_organizations_id_fk": {
          "name": "user_organizations_organization_id_organizations_id_fk",
          "tableFrom": "user_organizations",
          "tableTo": "organizations",
          "columnsFrom": [
            "organization_id"
          ],
          "columnsTo": [
            "id"
          ],
          "onDelete": "cascade",
          "onUpdate": "no action"
        }
      },
      "compositePrimaryKeys": {
        "user_organizations_user_id_organization_id_pk": {
          "name": "user_organizations_user_id_organization_id_pk",
          "columns": [
            "user_id",
            "organization_id"
          ]
        }
      },
      "uniqueConstraints": {},
      "policies": {},
      "checkConstraints": {},
      "isRLSEnabled": false
    }
  },
  "enums": {},
  "schemas": {},
  "sequences": {},
  "roles": {},
  "policies": {},
  "views": {},
  "_meta": {
    "columns": {},
    "schemas": {},
    "tables": {}
  }
}